differt/__init__.py
differt/_version.py
differt/py.typed
differt/utils.py
differt/em/__init__.py
differt/em/_antenna.py
differt/em/_constants.py
differt/em/_fresnel.py
differt/em/_interaction_type.py
differt/em/_material.py
differt/em/_utd.py
differt/em/_utils.py
differt/geometry/__init__.py
differt/geometry/_paths.py
differt/geometry/_triangle_mesh.py
differt/geometry/_utils.py
differt/plotting/__init__.py
differt/plotting/_core.py
differt/plotting/_utils.py
differt/plugins/__init__.py
differt/plugins/_deepmimo_types.py
differt/plugins/deepmimo.py
differt/rt/__init__.py
differt/rt/_fermat.py
differt/rt/_image_method.py
differt/rt/_utils.py
differt/scene/__init__.py
differt/scene/_sionna.py
differt/scene/_triangle_scene.py
differt-0.6.2.dist-info/METADATA
differt-0.6.2.dist-info/WHEEL
differt-0.6.2.dist-info/entry_points.txt
differt-0.6.2.dist-info/RECORD
