Metadata-Version: 2.4
Name: DiffeRT
Version: 0.6.2
Summary: Differentiable Ray Tracing Toolbox for Radio Propagation Simulations
Project-URL: Changelog, https://github.com/jeertmans/DiffeRT/releases
Project-URL: Documentation, https://eertmans.be/DiffeRT
Project-URL: Founding, https://github.com/sponsors/jeertmans
Project-URL: Homepage, https://github.com/jeertmans/DiffeRT
Project-URL: Repository, https://github.com/jeertmans/DiffeRT
Author-email: Jérome Eertmans <jeertmans@icloud.com>
License-Expression: MIT
Keywords: differentiable,jax,propagation,radio,ray tracing
Classifier: Operating System :: OS Independent
Classifier: Programming Language :: Python :: 3
Classifier: Programming Language :: Python :: 3.11
Classifier: Programming Language :: Python :: 3.12
Classifier: Programming Language :: Python :: 3.13
Classifier: Programming Language :: Python :: 3.14
Classifier: Programming Language :: Python :: Free Threading
Classifier: Topic :: Scientific/Engineering
Requires-Python: >=3.11
Requires-Dist: chex>=0.1.86
Requires-Dist: differt-core==0.6.2
Requires-Dist: equinox>=0.13.1
Requires-Dist: filelock>=3.15.4
Requires-Dist: fpt-jax==0.1.0
Requires-Dist: jax>=0.7.2
Requires-Dist: jaxtyping>=0.3.2
Requires-Dist: numpy>=1.26.1
Requires-Dist: requests>=2.32.0
Requires-Dist: tqdm>=4.66.2
Provides-Extra: all
Requires-Dist: ipympl>=0.9.4; extra == 'all'
Requires-Dist: jupyter-rfb>=0.4.2; extra == 'all'
Requires-Dist: matplotlib>=3.8.1; extra == 'all'
Requires-Dist: notebook>5; extra == 'all'
Requires-Dist: plotly>=5.18.0; extra == 'all'
Requires-Dist: pyopengl>=3.1.0; (platform_system == 'Darwin') and extra == 'all'
Requires-Dist: pyqt6>=6.6.1; extra == 'all'
Requires-Dist: vispy>=0.14.1; extra == 'all'
Provides-Extra: jupyter
Requires-Dist: ipympl>=0.9.4; extra == 'jupyter'
Requires-Dist: jupyter-rfb>=0.4.2; extra == 'jupyter'
Requires-Dist: notebook>5; extra == 'jupyter'
Provides-Extra: matplotlib
Requires-Dist: matplotlib>=3.8.1; extra == 'matplotlib'
Provides-Extra: plotly
Requires-Dist: plotly>=5.18.0; extra == 'plotly'
Provides-Extra: vispy
Requires-Dist: pyopengl>=3.1.0; (platform_system == 'Darwin') and extra == 'vispy'
Requires-Dist: vispy>=0.14.1; extra == 'vispy'
Provides-Extra: vispy-backend
Requires-Dist: pyqt6>=6.6.1; extra == 'vispy-backend'
